[{"@id":"501","@type":"m:BlockBreak","begin":1477059870636,"end":1477059870636,"m:x":484,"m:y":10,"m:z":22,"m:playerName":"Datcu","m:blockName":"STONE"},{"@id":"502","@type":"m:BlockBreak","begin":1477059871537,"end":1477059871537,"m:x":484,"m:y":11,"m:z":22,"m:playerName":"Datcu","m:blockName":"STONE"},{"@id":"503","@type":"m:BlockBreak","begin":1477059872444,"end":1477059872444,"m:x":484,"m:y":11,"m:z":21,"m:playerName":"Datcu","m:blockName":"STONE"},{"@id":"504","@type":"m:BlockBreak","begin":1477059873374,"end":1477059873374,"m:x":484,"m:y":10,"m:z":21,"m:playerName":"Datcu","m:blockName":"STONE"},{"@id":"505","@type":"m:BlockBreak","begin":1477059874228,"end":1477059874228,"m:x":484,"m:y":10,"m:z":20,"m:playerName":"Datcu","m:blockName":"STONE"},{"@id":"506","@type":"m:BlockBreak","begin":1477059875130,"end":1477059875130,"m:x":484,"m:y":11,"m:z":20,"m:playerName":"Datcu","m:blockName":"STONE"},{"@id":"507","@type":"m:BlockBreak","begin":1477059876032,"end":1477059876032,"m:x":484,"m:y":11,"m:z":19,"m:playerName":"Datcu","m:blockName":"STONE"},{"@id":"508","@type":"m:BlockBreak","begin":1477059877084,"end":1477059877084,"m:x":484,"m:y":10,"m:z":19,"m:playerName":"Datcu","m:blockName":"STONE"},{"@id":"509","@type":"m:PickupItem","begin":1477059877837,"end":1477059877837,"m:x":484,"m:y":8,"m:z":19,"m:playerName":"Datcu","m:itemName":"COBBLESTONE","m:amount":8},{"@id":"510","@type":"m:BlockPlace","begin":1477059879691,"end":1477059879691,"m:x":484,"m:y":8,"m:z":19,"m:playerName":"Datcu","m:data":5,"m:blockName":"TORCH"},{"@id":"511","@type":"m:BlockPlace","begin":1477059881139,"end":1477059881139,"m:x":484,"m:y":8,"m:z":24,"m:playerName":"Datcu","m:data":5,"m:blockName":"TORCH"},{"@id":"512","@type":"m:BlockBreak","begin":1477059884653,"end":1477059884653,"m:x":482,"m:y":8,"m:z":27,"m:playerName":"Datcu","m:blockName":"STONE"},{"@id":"513","@type":"m:PickupItem","begin":1477059885256,"end":1477059885256,"m:x":482,"m:y":8,"m:z":27,"m:playerName":"Datcu","m:itemName":"COBBLESTONE","m:amount":1},{"@id":"514","@type":"m:BlockBreak","begin":1477059886809,"end":1477059886809,"m:x":484,"m:y":11,"m:z":28,"m:playerName":"Datcu","m:data":1,"m:blockName":"STONE"},{"@id":"515","@type":"m:BlockBreak","begin":1477059887762,"end":1477059887762,"m:x":484,"m:y":10,"m:z":28,"m:playerName":"Datcu","m:data":1,"m:blockName":"STONE"},{"@id":"516","@type":"m:BlockBreak","begin":1477059888764,"end":1477059888764,"m:x":484,"m:y":9,"m:z":28,"m:playerName":"Datcu","m:blockName":"STONE"},{"@id":"517","@type":"m:BlockBreak","begin":1477059889666,"end":1477059889666,"m:x":484,"m:y":8,"m:z":28,"m:playerName":"Datcu","m:blockName":"STONE"},{"@id":"518","@type":"m:PickupItem","begin":1477059889818,"end":1477059889818,"m:x":484,"m:y":8,"m:z":28,"m:playerName":"Datcu","m:data":1,"m:itemName":"STONE","m:amount":2},{"@id":"519","@type":"m:BlockBreak","begin":1477059890568,"end":1477059890568,"m:x":484,"m:y":9,"m:z":29,"m:playerName":"Datcu","m:blockName":"STONE"},{"@id":"520","@type":"m:BlockBreak","begin":1477059891469,"end":1477059891469,"m:x":484,"m:y":10,"m:z":29,"m:playerName":"Datcu","m:blockName":"STONE"},{"@id":"521","@type":"m:BlockBreak","begin":1477059892371,"end":1477059892371,"m:x":484,"m:y":11,"m:z":29,"m:playerName":"Datcu","m:data":1,"m:blockName":"STONE"},{"@id":"522","@type":"m:BlockBreak","begin":1477059893272,"end":1477059893272,"m:x":484,"m:y":10,"m:z":30,"m:playerName":"Datcu","m:blockName":"STONE"},{"@id":"523","@type":"m:BlockBreak","begin":1477059894275,"end":1477059894275,"m:x":484,"m:y":9,"m:z":30,"m:playerName":"Datcu","m:blockName":"STONE"},{"@id":"524","@type":"m:BlockBreak","begin":1477059895176,"end":1477059895176,"m:x":484,"m:y":9,"m:z":31,"m:playerName":"Datcu","m:blockName":"STONE"},{"@id":"525","@type":"m:BlockBreak","begin":1477059896831,"end":1477059896831,"m:x":484,"m:y":8,"m:z":29,"m:playerName":"Datcu","m:blockName":"STONE"},{"@id":"526","@type":"m:BlockBreak","begin":1477059897733,"end":1477059897733,"m:x":484,"m:y":8,"m:z":30,"m:playerName":"Datcu","m:blockName":"STONE"},{"@id":"527","@type":"m:BlockBreak","begin":1477059898985,"end":1477059898985,"m:x":484,"m:y":11,"m:z":30,"m:playerName":"Datcu","m:data":1,"m:blockName":"STONE"},{"@id":"528","@type":"m:BlockBreak","begin":1477059900737,"end":1477059900737,"m:x":484,"m:y":10,"m:z":31,"m:playerName":"Datcu","m:blockName":"STONE"},{"@id":"529","@type":"m:BlockBreak","begin":1477059902642,"end":1477059902642,"m:x":484,"m:y":8,"m:z":31,"m:playerName":"Datcu","m:blockName":"STONE"},{"@id":"530","@type":"m:PickupItem","begin":1477059904396,"end":1477059904396,"m:x":484,"m:y":8,"m:z":29,"m:playerName":"Datcu","m:data":1,"m:itemName":"STONE","m:amount":2},{"@id":"531","@type":"m:PickupItem","begin":1477059904698,"end":1477059904698,"m:x":484,"m:y":8,"m:z":31,"m:playerName":"Datcu","m:itemName":"COBBLESTONE","m:amount":11},{"@id":"532","@type":"m:BlockBreak","begin":1477059909007,"end":1477059909007,"m:x":484,"m:y":11,"m:z":31,"m:playerName":"Datcu","m:data":1,"m:blockName":"STONE"},{"@id":"533","@type":"m:BlockBreak","begin":1477059909910,"end":1477059909910,"m:x":484,"m:y":11,"m:z":32,"m:playerName":"Datcu","m:blockName":"STONE"},{"@id":"534","@type":"m:BlockBreak","begin":1477059911062,"end":1477059911062,"m:x":484,"m:y":10,"m:z":32,"m:playerName":"Datcu","m:blockName":"STONE"},{"@id":"535","@type":"m:BlockBreak","begin":1477059911963,"end":1477059911963,"m:x":484,"m:y":10,"m:z":33,"m:playerName":"Datcu","m:blockName":"STONE"},{"@id":"536","@type":"m:BlockBreak","begin":1477059912864,"end":1477059912864,"m:x":484,"m:y":11,"m:z":33,"m:playerName":"Datcu","m:blockName":"STONE"},{"@id":"537","@type":"m:BlockBreak","begin":1477059914068,"end":1477059914068,"m:x":484,"m:y":9,"m:z":32,"m:playerName":"Datcu","m:blockName":"STONE"},{"@id":"538","@type":"m:BlockBreak","begin":1477059914970,"end":1477059914970,"m:x":484,"m:y":8,"m:z":32,"m:playerName":"Datcu","m:blockName":"STONE"},{"@id":"539","@type":"m:BlockBreak","begin":1477059915872,"end":1477059915872,"m:x":484,"m:y":8,"m:z":33,"m:playerName":"Datcu","m:blockName":"STONE"},{"@id":"540","@type":"m:BlockBreak","begin":1477059916776,"end":1477059916776,"m:x":484,"m:y":9,"m:z":33,"m:playerName":"Datcu","m:blockName":"STONE"},{"@id":"541","@type":"m:PickupItem","begin":1477059917478,"end":1477059917478,"m:x":484,"m:y":8,"m:z":31,"m:playerName":"Datcu","m:data":1,"m:itemName":"STONE","m:amount":1},{"@id":"542","@type":"m:PickupItem","begin":1477059917979,"end":1477059917979,"m:x":484,"m:y":8,"m:z":33,"m:playerName":"Datcu","m:itemName":"COBBLESTONE","m:amount":8},{"@id":"543","@type":"m:BlockPlace","begin":1477059920716,"end":1477059920716,"m:x":484,"m:y":8,"m:z":33,"m:playerName":"Datcu","m:data":5,"m:blockName":"TORCH"},{"@id":"544","@type":"m:BlockPlace","begin":1477059922721,"end":1477059922721,"m:x":484,"m:y":8,"m:z":28,"m:playerName":"Datcu","m:data":5,"m:blockName":"TORCH"},{"@id":"545","@type":"m:BlockBreak","begin":1477059930837,"end":1477059930837,"m:x":484,"m:y":7,"m:z":31,"m:playerName":"Datcu","m:blockName":"GLOWING_REDSTONE_ORE"},{"@id":"546","@type":"m:BlockBreak","begin":1477059931891,"end":1477059931891,"m:x":484,"m:y":7,"m:z":32,"m:playerName":"Datcu","m:blockName":"GLOWING_REDSTONE_ORE"},{"@id":"547","@type":"m:PickupItem","begin":1477059932394,"end":1477059932394,"m:x":484,"m:y":7,"m:z":31,"m:playerName":"Datcu","m:itemName":"REDSTONE","m:amount":7},{"@id":"548","@type":"m:BlockBreak","begin":1477059933296,"end":1477059933296,"m:x":483,"m:y":7,"m:z":32,"m:playerName":"Datcu","m:blockName":"GLOWING_REDSTONE_ORE"},{"@id":"549","@type":"m:BlockBreak","begin":1477059934600,"end":1477059934600,"m:x":484,"m:y":6,"m:z":32,"m:playerName":"Datcu","m:blockName":"GLOWING_REDSTONE_ORE"},{"@id":"550","@type":"m:BlockBreak","begin":1477059935651,"end":1477059935651,"m:x":483,"m:y":6,"m:z":32,"m:playerName":"Datcu","m:blockName":"GLOWING_REDSTONE_ORE"},{"@id":"551","@type":"m:PickupItem","begin":1477059936555,"end":1477059936555,"m:x":484,"m:y":6,"m:z":32,"m:playerName":"Datcu","m:itemName":"REDSTONE","m:amount":12},{"@id":"552","@type":"m:BlockBreak","begin":1477059937753,"end":1477059937753,"m:x":483,"m:y":7,"m:z":31,"m:playerName":"Datcu","m:blockName":"GLOWING_REDSTONE_ORE"},{"@id":"553","@type":"m:PickupItem","begin":1477059938255,"end":1477059938255,"m:x":483,"m:y":6,"m:z":32,"m:playerName":"Datcu","m:itemName":"REDSTONE","m:amount":7},{"@id":"554","@type":"m:BlockBreak","begin":1477059938806,"end":1477059938806,"m:x":483,"m:y":6,"m:z":31,"m:playerName":"Datcu","m:blockName":"GLOWING_REDSTONE_ORE"},{"@id":"555","@type":"m:BlockBreak","begin":1477059939958,"end":1477059939958,"m:x":484,"m:y":6,"m:z":31,"m:playerName":"Datcu","m:blockName":"GLOWING_REDSTONE_ORE"},{"@id":"556","@type":"m:PickupItem","begin":1477059940012,"end":1477059940012,"m:x":483,"m:y":6,"m:z":31,"m:playerName":"Datcu","m:itemName":"REDSTONE","m:amount":5},{"@id":"557","@type":"m:PickupItem","begin":1477059940460,"end":1477059940460,"m:x":484,"m:y":6,"m:z":32,"m:playerName":"Datcu","m:itemName":"REDSTONE","m:amount":4},{"@id":"558","@type":"m:BlockBreak","begin":1477059941460,"end":1477059941460,"m:x":484,"m:y":5,"m:z":32,"m:playerName":"Datcu","m:blockName":"GLOWING_REDSTONE_ORE"},{"@id":"559","@type":"m:PickupItem","begin":1477059942463,"end":1477059942463,"m:x":484,"m:y":5,"m:z":32,"m:playerName":"Datcu","m:itemName":"REDSTONE","m:amount":1},{"@id":"560","@type":"m:PickupItem","begin":1477059942464,"end":1477059942464,"m:x":484,"m:y":5,"m:z":32,"m:playerName":"Datcu","m:itemName":"REDSTONE","m:amount":1},{"@id":"561","@type":"m:PickupItem","begin":1477059942464,"end":1477059942464,"m:x":484,"m:y":5,"m:z":32,"m:playerName":"Datcu","m:itemName":"REDSTONE","m:amount":1},{"@id":"562","@type":"m:PickupItem","begin":1477059942465,"end":1477059942465,"m:x":484,"m:y":5,"m:z":32,"m:playerName":"Datcu","m:itemName":"REDSTONE","m:amount":1},{"@id":"563","@type":"m:BlockPlace","begin":1477059945369,"end":1477059945369,"m:x":484,"m:y":5,"m:z":32,"m:playerName":"Datcu","m:blockName":"COBBLESTONE"},{"@id":"564","@type":"m:BlockPlace","begin":1477059945870,"end":1477059945870,"m:x":483,"m:y":6,"m:z":32,"m:playerName":"Datcu","m:blockName":"COBBLESTONE"},{"@id":"565","@type":"m:BlockPlace","begin":1477059946220,"end":1477059946220,"m:x":483,"m:y":6,"m:z":31,"m:playerName":"Datcu","m:blockName":"COBBLESTONE"},{"@id":"566","@type":"m:BlockPlace","begin":1477059946622,"end":1477059946622,"m:x":483,"m:y":7,"m:z":32,"m:playerName":"Datcu","m:blockName":"COBBLESTONE"},{"@id":"567","@type":"m:BlockPlace","begin":1477059946872,"end":1477059946872,"m:x":483,"m:y":7,"m:z":31,"m:playerName":"Datcu","m:blockName":"COBBLESTONE"},{"@id":"568","@type":"m:BlockPlace","begin":1477059947423,"end":1477059947423,"m:x":484,"m:y":6,"m:z":31,"m:playerName":"Datcu","m:blockName":"COBBLESTONE"},{"@id":"569","@type":"m:BlockPlace","begin":1477059948023,"end":1477059948023,"m:x":484,"m:y":6,"m:z":32,"m:playerName":"Datcu","m:blockName":"COBBLESTONE"},{"@id":"570","@type":"m:BlockPlace","begin":1477059948624,"end":1477059948624,"m:x":484,"m:y":7,"m:z":32,"m:playerName":"Datcu","m:blockName":"COBBLESTONE"},{"@id":"571","@type":"m:BlockPlace","begin":1477059950075,"end":1477059950075,"m:x":484,"m:y":7,"m:z":31,"m:playerName":"Datcu","m:blockName":"COBBLESTONE"},{"@id":"572","@type":"m:BlockBreak","begin":1477059965903,"end":1477059965903,"m:x":485,"m:y":8,"m:z":26,"m:playerName":"Datcu","m:blockName":"STONE"},{"@id":"573","@type":"m:BlockBreak","begin":1477059968419,"end":1477059968419,"m:x":485,"m:y":9,"m:z":26,"m:playerName":"Datcu","m:blockName":"STONE"},{"@id":"574","@type":"m:BlockBreak","begin":1477059969345,"end":1477059969345,"m:x":486,"m:y":9,"m:z":26,"m:playerName":"Datcu","m:blockName":"STONE"},{"@id":"575","@type":"m:BlockBreak","begin":1477059970248,"end":1477059970248,"m:x":486,"m:y":8,"m:z":26,"m:playerName":"Datcu","m:blockName":"STONE"},{"@id":"576","@type":"m:PickupItem","begin":1477059970752,"end":1477059970752,"m:x":485,"m:y":8,"m:z":26,"m:playerName":"Datcu","m:itemName":"COBBLESTONE","m:amount":4},{"@id":"577","@type":"m:BlockBreak","begin":1477059971151,"end":1477059971151,"m:x":487,"m:y":9,"m:z":26,"m:playerName":"Datcu","m:blockName":"STONE"},{"@id":"578","@type":"m:PickupItem","begin":1477059971653,"end":1477059971653,"m:x":487,"m:y":9,"m:z":26,"m:playerName":"Datcu","m:itemName":"COBBLESTONE","m:amount":1},{"@id":"579","@type":"m:BlockBreak","begin":1477059974108,"end":1477059974108,"m:x":487,"m:y":8,"m:z":26,"m:playerName":"Datcu","m:blockName":"DIAMOND_ORE"},{"@id":"580","@type":"m:PickupItem","begin":1477059974611,"end":1477059974611,"m:x":487,"m:y":8,"m:z":26,"m:playerName":"Datcu","m:itemName":"DIAMOND","m:amount":1},{"@id":"581","@type":"m:BlockBreak","begin":1477059977063,"end":1477059977063,"m:x":488,"m:y":8,"m:z":26,"m:playerName":"Datcu","m:blockName":"DIAMOND_ORE"},{"@id":"582","@type":"m:PickupItem","begin":1477059977565,"end":1477059977565,"m:x":488,"m:y":8,"m:z":26,"m:playerName":"Datcu","m:itemName":"DIAMOND","m:amount":1},{"@id":"583","@type":"m:BlockBreak","begin":1477059980370,"end":1477059980370,"m:x":488,"m:y":9,"m:z":26,"m:playerName":"Datcu","m:blockName":"STONE"},{"@id":"584","@type":"m:BlockPlace","begin":1477059983126,"end":1477059983126,"m:x":487,"m:y":8,"m:z":26,"m:playerName":"Datcu","m:blockName":"COBBLESTONE"},{"@id":"585","@type":"m:BlockBreak","begin":1477059988094,"end":1477059988094,"m:x":485,"m:y":11,"m:z":26,"m:playerName":"Datcu","m:data":1,"m:blockName":"STONE"},{"@id":"586","@type":"m:BlockBreak","begin":1477059988996,"end":1477059988996,"m:x":486,"m:y":11,"m:z":26,"m:playerName":"Datcu","m:data":1,"m:blockName":"STONE"},{"@id":"587","@type":"m:BlockBreak","begin":1477059992255,"end":1477059992255,"m:x":484,"m:y":12,"m:z":26,"m:playerName":"Datcu","m:data":1,"m:blockName":"STONE"},{"@id":"588","@type":"m:BlockBreak","begin":1477059993156,"end":1477059993156,"m:x":485,"m:y":12,"m:z":26,"m:playerName":"Datcu","m:data":1,"m:blockName":"STONE"},{"@id":"589","@type":"m:PickupItem","begin":1477059993358,"end":1477059993358,"m:x":484,"m:y":8,"m:z":27,"m:playerName":"Datcu","m:data":1,"m:itemName":"STONE","m:amount":3},{"@id":"590","@type":"m:BlockBreak","begin":1477059994711,"end":1477059994711,"m:x":485,"m:y":10,"m:z":26,"m:playerName":"Datcu","m:data":1,"m:blockName":"STONE"},{"@id":"591","@type":"m:BlockBreak","begin":1477059995613,"end":1477059995613,"m:x":486,"m:y":10,"m:z":26,"m:playerName":"Datcu","m:blockName":"STONE"},{"@id":"592","@type":"m:BlockBreak","begin":1477059996513,"end":1477059996513,"m:x":487,"m:y":11,"m:z":26,"m:playerName":"Datcu","m:blockName":"STONE"},{"@id":"593","@type":"m:BlockPlace","begin":1477060001127,"end":1477060001127,"m:x":486,"m:y":8,"m:z":26,"m:playerName":"Datcu","m:blockName":"COBBLESTONE"},{"@id":"594","@type":"m:PickupItem","begin":1477060001480,"end":1477060001480,"m:x":485,"m:y":8,"m:z":26,"m:playerName":"Datcu","m:itemName":"COBBLESTONE","m:amount":1},{"@id":"595","@type":"m:BlockPlace","begin":1477060001729,"end":1477060001729,"m:x":486,"m:y":9,"m:z":26,"m:playerName":"Datcu","m:blockName":"COBBLESTONE"},{"@id":"596","@type":"m:BlockPlace","begin":1477060002230,"end":1477060002230,"m:x":485,"m:y":8,"m:z":26,"m:playerName":"Datcu","m:blockName":"COBBLESTONE"},{"@id":"597","@type":"m:PickupItem","begin":1477060002282,"end":1477060002282,"m:x":485,"m:y":7,"m:z":26,"m:playerName":"Datcu","m:data":1,"m:itemName":"STONE","m:amount":2},{"@id":"598","@type":"m:PickupItem","begin":1477060002986,"end":1477060002986,"m:x":486,"m:y":11,"m:z":26,"m:playerName":"Datcu","m:itemName":"COBBLESTONE","m:amount":1},{"@id":"599","@type":"m:BlockBreak","begin":1477060062474,"end":1477060062474,"m:x":487,"m:y":12,"m:z":26,"m:playerName":"Datcu","m:blockName":"STONE"},{"@id":"600","@type":"m:PickupItem","begin":1477060062978,"end":1477060062978,"m:x":487,"m:y":11,"m:z":26,"m:playerName":"Datcu","m:itemName":"COBBLESTONE","m:amount":1}]